qmuvi/__init__.py
qmuvi/data_manager.py
qmuvi/musical_processing.py
qmuvi/package_data/assets/black.png
qmuvi/package_data/assets/white.png
qmuvi/package_data/binaries/TiMidity-2.15.0/COPYING.txt
qmuvi/package_data/binaries/TiMidity-2.15.0/macos/timidity
qmuvi/package_data/binaries/TiMidity-2.15.0/windows/timidity.exe
qmuvi/package_data/resources/GeneralUser_GS_1.471/CHANGELOG.txt
qmuvi/package_data/resources/GeneralUser_GS_1.471/GeneralUser_GS_v1.471.sf2
qmuvi/package_data/resources/GeneralUser_GS_1.471/GUTest.mid
qmuvi/package_data/resources/GeneralUser_GS_1.471/instrument lists/Cakewalk_SONAR/GeneralUser GS 1.43-Drumsets.ins
qmuvi/package_data/resources/GeneralUser_GS_1.471/instrument lists/Cakewalk_SONAR/GeneralUser GS 1.43.ins
qmuvi/package_data/resources/GeneralUser_GS_1.471/instrument lists/GU1.43 Percussion Map.pdf
qmuvi/package_data/resources/GeneralUser_GS_1.471/instrument lists/Rosegarden/GeneralUser_GS_1.43.rgd
qmuvi/package_data/resources/GeneralUser_GS_1.471/LICENSE.txt
qmuvi/package_data/resources/GeneralUser_GS_1.471/README.txt
qmuvi/package_data/resources/timidity/timidity.cfg
qmuvi/package_data/source/TiMidity-2.15.0/AUTHORS
qmuvi/package_data/source/TiMidity-2.15.0/autoconf/alsa.m4
qmuvi/package_data/source/TiMidity-2.15.0/autoconf/ao.m4
qmuvi/package_data/source/TiMidity-2.15.0/autoconf/arts.m4
qmuvi/package_data/source/TiMidity-2.15.0/autoconf/esd.m4
qmuvi/package_data/source/TiMidity-2.15.0/autoconf/gtk-2.0.m4
qmuvi/package_data/source/TiMidity-2.15.0/autoconf/gtk.m4
qmuvi/package_data/source/TiMidity-2.15.0/autoconf/libFLAC.m4
qmuvi/package_data/source/TiMidity-2.15.0/autoconf/libOggFLAC.m4
qmuvi/package_data/source/TiMidity-2.15.0/autoconf/Makefile.am
qmuvi/package_data/source/TiMidity-2.15.0/autoconf/ogg.m4
qmuvi/package_data/source/TiMidity-2.15.0/autoconf/utils.m4
qmuvi/package_data/source/TiMidity-2.15.0/autoconf/vorbis.m4
qmuvi/package_data/source/TiMidity-2.15.0/autogen.sh
qmuvi/package_data/source/TiMidity-2.15.0/ChangeLog.1
qmuvi-0.3.0.dist-info/LICENSE.txt
qmuvi-0.3.0.dist-info/METADATA
qmuvi-0.3.0.dist-info/WHEEL
qmuvi-0.3.0.dist-info/RECORD
