Metadata-Version: 2.1
Name: qmuvi
Version: 0.3.0
Summary: qMuVi is a Python library that converts quantum circuits into music videos, enabling visualisation of quantum state evolution through sound and animation. It supports noise models to simulate physical quantum devices and displays animating probability and phase distributions of basis states.
Home-page: https://garymooney.github.io/qmuvi/
License: LGPL-2.1-or-later
Author: Gary Mooney
Author-email: gary.mooney4444@gmail.com
Requires-Python: >=3.9,<4.0
Classifier: Development Status :: 2 - Pre-Alpha
Classifier: Intended Audience :: Developers
Classifier: Intended Audience :: Education
Classifier: Intended Audience :: Science/Research
Classifier: License :: OSI Approved
Classifier: License :: OSI Approved :: GNU Library or Lesser General Public License (LGPL)
Classifier: Natural Language :: English
Classifier: Programming Language :: Python :: 3
Classifier: Programming Language :: Python :: 3.9
Classifier: Programming Language :: Python :: 3.10
Classifier: Programming Language :: Python :: 3.11
Classifier: Programming Language :: Python :: 3.10
Classifier: Programming Language :: Python :: 3.11
Classifier: Programming Language :: Python :: 3.9
Provides-Extra: dev
Provides-Extra: doc
Provides-Extra: test
Requires-Dist: black (>=22.3.0,<23.0.0) ; extra == "dev"
Requires-Dist: flake8 (>=6.0.0,<7.0.0) ; extra == "dev"
Requires-Dist: isort (==5.10.1) ; extra == "dev"
Requires-Dist: livereload (>=2.6.3,<3.0.0) ; extra == "doc"
Requires-Dist: matplotlib (>=3.6.2,<4.0.0)
Requires-Dist: mido (>=1.2.10,<2.0.0)
Requires-Dist: moviepy (>=2.2.1,<3.0.0)
Requires-Dist: myst-parser (>=1.0.0,<2.0.0) ; extra == "doc"
Requires-Dist: numpy (>=1.24.0,<2.0.0)
Requires-Dist: pip (>=22.0.3,<23.0.0) ; extra == "dev"
Requires-Dist: pipdeptree (>=2.7.0,<3.0.0) ; extra == "dev"
Requires-Dist: pylatexenc (>=2.10,<3.0)
Requires-Dist: pytest (>=7.0.1,<8.0.0) ; extra == "test"
Requires-Dist: pytest-cov (>=3.0.0,<4.0.0) ; extra == "test"
Requires-Dist: pytest-mock (>=3.10.0,<4.0.0) ; extra == "test"
Requires-Dist: qiskit (>=2.1.2,<3.0.0)
Requires-Dist: qiskit_aer (>=0.17.0)
Requires-Dist: sphinx (>=6.1.3,<7.0.0) ; extra == "doc"
Requires-Dist: sphinx-autodoc-typehints (>=1.22,<2.0) ; extra == "doc"
Requires-Dist: sphinx-rtd-theme (>=1.2.0,<2.0.0) ; extra == "doc"
Requires-Dist: toml (>=0.10.2,<0.11.0) ; extra == "dev"
Requires-Dist: tox (>=4.4.12,<5.0.0) ; extra == "dev"
Requires-Dist: tox-gh-actions (>=3.1.0,<4.0.0)
Requires-Dist: twine (>=3.8.0,<4.0.0) ; extra == "dev"
Requires-Dist: virtualenv (>=20.13.1,<21.0.0) ; extra == "dev"
Project-URL: Repository, https://github.com/garymooney/qmuvi
